annotation_parser/__init__.py
annotation_parser/adapters/__init__.py
annotation_parser/adapters/adapter_factory.py
annotation_parser/adapters/adapter_registration.py
annotation_parser/adapters/base_adapter.py
annotation_parser/adapters/coco_adapter.py
annotation_parser/adapters/labelme_adapter.py
annotation_parser/adapters/voc_adapter.py
annotation_parser/api/__init__.py
annotation_parser/api/api.py
annotation_parser/api/parser_api.py
annotation_parser/api/saver_api.py
annotation_parser/api/shapes_api.py
annotation_parser/cli.py
annotation_parser/core/__init__.py
annotation_parser/core/annotation_file.py
annotation_parser/core/annotation_parser.py
annotation_parser/core/annotation_saver.py
annotation_parser/models/__init__.py
annotation_parser/models/coco_model.py
annotation_parser/models/labelme_model.py
annotation_parser/models/voc_model.py
annotation_parser/public_enums.py
annotation_parser/shape.py
annotation_parser/types.py
annotation_parser/utils/__init__.py
annotation_parser/utils/geometry.py
annotation_parser-0.1.0.dist-info/entry_points.txt
annotation_parser-0.1.0.dist-info/LICENSE
annotation_parser-0.1.0.dist-info/METADATA
annotation_parser-0.1.0.dist-info/WHEEL
annotation_parser-0.1.0.dist-info/RECORD
