Metadata-Version: 2.3
Name: annotation-parser
Version: 0.1.0
Summary: AnnotationParser is a universal Python library that parses annotation files from different formats (LabelMe, COCO, VOC, etc.) into a single unified Shape data structure. This allows you to work with annotations using a consistent interface, regardless of the original format.
License: MIT
Keywords: annotation,annotations,annotation-tool,labelme,labelme-annotations,labelme-json,parser,dataset,coco,voc,yolo,cvat,roboflow
Author: migutin83
Author-email: migutin83@yandex.ru
Requires-Python: >=3.10
Classifier: Programming Language :: Python :: 3
Classifier: License :: OSI Approved :: MIT License
Classifier: Operating System :: OS Independent
Classifier: Intended Audience :: Developers
Classifier: Topic :: Software Development :: Libraries
Classifier: Topic :: Scientific/Engineering :: Artificial Intelligence
Requires-Dist: pydantic (>=2.11.7,<3.0.0)
Requires-Dist: shapely (>=2.1.1,<3.0.0)
Project-URL: Bug Tracker, https://github.com/omigutin/annotation_parser/issues
Project-URL: Homepage, https://github.com/omigutin/annotation_parser
